Mtripix/Mutils.py
Mtripix/__init__.py
Mtripix-0.1.0.dist-info/METADATA
Mtripix-0.1.0.dist-info/WHEEL
Mtripix-0.1.0.dist-info/top_level.txt
Mtripix-0.1.0.dist-info/RECORD
