Metadata-Version: 2.1
Name: Mtripix
Version: 0.1.0
Summary: api handle for data transform
Author: TriplePixels
Author-email: PIPIPINoBrain@163.com
License: apache 3.0
Requires: numpy
Requires: json
Requires: lxml
Requires: PIL
Requires: imgviz
Requires: opencv
Requires: math
